.gitignore
LICENSE
README.md
mkdocs.yml
setup.py
astr3510/__init__.py
astr3510/bucket.py
astr3510/gaia.py
astr3510/imports.py
astr3510/transit.py
astr3510/version.py
astr3510/in-progress/ccd.py
astr3510/in-progress/imaging.py
astr3510/in-progress/logs.py
astr3510/in-progress/loupe.py
astr3510/psfs/__init__.py
astr3510/psfs/apertures.py
astr3510/psfs/image.py
astr3510/tests/test_bucket.py
astr3510/tests/test_gaia.py
astr3510/tests/test_transit.py
cu_astr3510.egg-info/PKG-INFO
cu_astr3510.egg-info/SOURCES.txt
cu_astr3510.egg-info/dependency_links.txt
cu_astr3510.egg-info/not-zip-safe
cu_astr3510.egg-info/requires.txt
cu_astr3510.egg-info/top_level.txt
docs/contributing.ipynb
docs/gaia.ipynb
docs/index.md
docs/installation.ipynb
docs/pdf-plots.ipynb
docs/reference.md
docs/basics/color-images.ipynb
docs/basics/fits-files.ipynb
docs/basics/plots.ipynb
docs/basics/rainbow.jpg
docs/basics/units.ipynb
docs/concepts/catching-photons.ipynb
docs/concepts/chi-squared-fitting.ipynb
docs/concepts/leavitt-computers.jpg
docs/concepts/leavitt-periods.csv
docs/concepts/leavitt-text.png
docs/tools/gaia.ipynb